{
 "custom_fields": [
  {
   "_assign": null,
   "_comments": null,
   "_liked_by": null,
   "_user_tags": null,
   "allow_on_submit": 0,
   "bold": 0,
   "collapsible": 0,
   "collapsible_depends_on": null,
   "columns": 0,
   "creation": "2019-10-24 10:42:52.005861",
   "default": null,
   "depends_on": null,
   "description": null,
   "docstatus": 0,
   "dt": "Purchase Invoice",
   "fetch_from": null,
   "fetch_if_empty": 0,
   "fieldname": "multilevel_discount_percentage",
   "fieldtype": "Data",
   "hidden": 0,
   "idx": 90,
   "ignore_user_permissions": 0,
   "ignore_xss_filter": 0,
   "in_global_search": 0,
   "in_list_view": 0,
   "in_standard_filter": 0,
   "insert_after": "column_break_46",
   "label": "Multilevel Discount Percentage",
   "modified": "2019-10-24 10:42:52.005861",
   "modified_by": "Administrator",
   "name": "Purchase Invoice-multilevel_discount_percentage",
   "no_copy": 0,
   "options": null,
   "owner": "Administrator",
   "parent": null,
   "parentfield": null,
   "parenttype": null,
   "permlevel": 0,
   "precision": "",
   "print_hide": 0,
   "print_hide_if_no_value": 0,
   "print_width": null,
   "read_only": 0,
   "report_hide": 0,
   "reqd": 0,
   "search_index": 0,
   "translatable": 0,
   "unique": 0,
   "width": null
  }
 ],
 "custom_perms": [],
 "doctype": "Purchase Invoice",
 "property_setters": [
  {
   "_assign": null,
   "_comments": null,
   "_liked_by": null,
   "_user_tags": null,
   "creation": "2019-10-24 10:28:10.224173",
   "default_value": null,
   "doc_type": "Purchase Invoice",
   "docstatus": 0,
   "doctype_or_field": "DocField",
   "field_name": "scan_barcode",
   "idx": 0,
   "modified": "2019-10-24 10:28:10.224173",
   "modified_by": "Administrator",
   "name": "Purchase Invoice-scan_barcode-hidden",
   "owner": "Administrator",
   "parent": null,
   "parentfield": null,
   "parenttype": null,
   "property": "hidden",
   "property_type": "Check",
   "value": "0"
  },
  {
   "_assign": null,
   "_comments": null,
   "_liked_by": null,
   "_user_tags": null,
   "creation": "2019-10-24 10:27:56.479113",
   "default_value": null,
   "doc_type": "Purchase Invoice",
   "docstatus": 0,
   "doctype_or_field": "DocField",
   "field_name": "in_words",
   "idx": 0,
   "modified": "2019-10-24 10:27:56.479113",
   "modified_by": "Administrator",
   "name": "Purchase Invoice-in_words-print_hide",
   "owner": "Administrator",
   "parent": null,
   "parentfield": null,
   "parenttype": null,
   "property": "print_hide",
   "property_type": "Check",
   "value": "0"
  },
  {
   "_assign": null,
   "_comments": null,
   "_liked_by": null,
   "_user_tags": null,
   "creation": "2019-10-24 10:27:56.247268",
   "default_value": null,
   "doc_type": "Purchase Invoice",
   "docstatus": 0,
   "doctype_or_field": "DocField",
   "field_name": "in_words",
   "idx": 0,
   "modified": "2019-10-24 10:27:56.247268",
   "modified_by": "Administrator",
   "name": "Purchase Invoice-in_words-hidden",
   "owner": "Administrator",
   "parent": null,
   "parentfield": null,
   "parenttype": null,
   "property": "hidden",
   "property_type": "Check",
   "value": "0"
  },
  {
   "_assign": null,
   "_comments": null,
   "_liked_by": null,
   "_user_tags": null,
   "creation": "2019-10-24 10:27:53.559224",
   "default_value": null,
   "doc_type": "Purchase Invoice",
   "docstatus": 0,
   "doctype_or_field": "DocField",
   "field_name": "rounded_total",
   "idx": 0,
   "modified": "2019-10-24 10:27:53.559224",
   "modified_by": "Administrator",
   "name": "Purchase Invoice-rounded_total-print_hide",
   "owner": "Administrator",
   "parent": null,
   "parentfield": null,
   "parenttype": null,
   "property": "print_hide",
   "property_type": "Check",
   "value": "0"
  },
  {
   "_assign": null,
   "_comments": null,
   "_liked_by": null,
   "_user_tags": null,
   "creation": "2019-10-24 10:27:53.319290",
   "default_value": null,
   "doc_type": "Purchase Invoice",
   "docstatus": 0,
   "doctype_or_field": "DocField",
   "field_name": "rounded_total",
   "idx": 0,
   "modified": "2019-10-24 10:27:53.319290",
   "modified_by": "Administrator",
   "name": "Purchase Invoice-rounded_total-hidden",
   "owner": "Administrator",
   "parent": null,
   "parentfield": null,
   "parenttype": null,
   "property": "hidden",
   "property_type": "Check",
   "value": "0"
  },
  {
   "_assign": null,
   "_comments": null,
   "_liked_by": null,
   "_user_tags": null,
   "creation": "2019-10-24 10:27:53.094933",
   "default_value": null,
   "doc_type": "Purchase Invoice",
   "docstatus": 0,
   "doctype_or_field": "DocField",
   "field_name": "base_rounded_total",
   "idx": 0,
   "modified": "2019-10-24 10:27:53.094933",
   "modified_by": "Administrator",
   "name": "Purchase Invoice-base_rounded_total-print_hide",
   "owner": "Administrator",
   "parent": null,
   "parentfield": null,
   "parenttype": null,
   "property": "print_hide",
   "property_type": "Check",
   "value": "1"
  },
  {
   "_assign": null,
   "_comments": null,
   "_liked_by": null,
   "_user_tags": null,
   "creation": "2019-10-24 10:27:52.844709",
   "default_value": null,
   "doc_type": "Purchase Invoice",
   "docstatus": 0,
   "doctype_or_field": "DocField",
   "field_name": "base_rounded_total",
   "idx": 0,
   "modified": "2019-10-24 10:27:52.844709",
   "modified_by": "Administrator",
   "name": "Purchase Invoice-base_rounded_total-hidden",
   "owner": "Administrator",
   "parent": null,
   "parentfield": null,
   "parenttype": null,
   "property": "hidden",
   "property_type": "Check",
   "value": "0"
  },
  {
   "_assign": null,
   "_comments": null,
   "_liked_by": null,
   "_user_tags": null,
   "creation": "2019-10-24 08:38:24.980673",
   "default_value": null,
   "doc_type": "Purchase Invoice",
   "docstatus": 0,
   "doctype_or_field": "DocField",
   "field_name": "cost_center",
   "idx": 0,
   "modified": "2019-10-24 08:38:24.980673",
   "modified_by": "Administrator",
   "name": "Purchase Invoice-cost_center-hidden",
   "owner": "Administrator",
   "parent": null,
   "parentfield": null,
   "parenttype": null,
   "property": "hidden",
   "property_type": "Check",
   "value": "1"
  },
  {
   "_assign": null,
   "_comments": null,
   "_liked_by": null,
   "_user_tags": null,
   "creation": "2019-10-24 08:38:24.522472",
   "default_value": null,
   "doc_type": "Purchase Invoice",
   "docstatus": 0,
   "doctype_or_field": "DocField",
   "field_name": "payment_schedule",
   "idx": 0,
   "modified": "2019-10-24 08:38:24.522472",
   "modified_by": "Administrator",
   "name": "Purchase Invoice-payment_schedule-print_hide",
   "owner": "Administrator",
   "parent": null,
   "parentfield": null,
   "parenttype": null,
   "property": "print_hide",
   "property_type": "Check",
   "value": "1"
  },
  {
   "_assign": null,
   "_comments": null,
   "_liked_by": null,
   "_user_tags": null,
   "creation": "2019-10-24 08:38:24.309062",
   "default_value": null,
   "doc_type": "Purchase Invoice",
   "docstatus": 0,
   "doctype_or_field": "DocField",
   "field_name": "due_date",
   "idx": 0,
   "modified": "2019-10-24 08:38:24.309062",
   "modified_by": "Administrator",
   "name": "Purchase Invoice-due_date-print_hide",
   "owner": "Administrator",
   "parent": null,
   "parentfield": null,
   "parenttype": null,
   "property": "print_hide",
   "property_type": "Check",
   "value": "0"
  }
 ],
 "sync_on_migrate": 1
}